[
  {
    "matchId": "b4e124f5-18b3-4d8d-9c85-43b2dd5415cd",
    "competition": "One-Day Cup",
    "homeTeam": "Leicestershire",
    "homeTeamBlueskyHandle": "leicsccc.bsky.social",
    "awayTeam": "Derbyshire",
    "awayTeamBlueskyHandle": null,
    "startDate": "2025-08-20",
    "endDate": "2025-08-20",
    "startTimeGmt": "10:00",
    "venue": "Grace Road, Leicester",
    "day": "One Day Match"
  },
  {
    "matchId": "f10b883f-ff20-4350-b6f8-be59c167f4a5",
    "competition": "One-Day Cup",
    "homeTeam": "Lancashire",
    "homeTeamBlueskyHandle": "lancscricket.bsky.social",
    "awayTeam": "Durham",
    "awayTeamBlueskyHandle": "durhamcricket.bsky.social",
    "startDate": "2025-08-20",
    "endDate": "2025-08-20",
    "startTimeGmt": "10:00",
    "venue": "TBC, TBC",
    "day": "One Day Match"
  },
  {
    "matchId": "b6bd4da9-ede0-4a6e-bc61-9e90161acfea",
    "competition": "One-Day Cup",
    "homeTeam": "Hampshire",
    "homeTeamBlueskyHandle": "hampshirecricket.bsky.social",
    "awayTeam": "Nottinghamshire",
    "awayTeamBlueskyHandle": null,
    "startDate": "2025-08-20",
    "endDate": "2025-08-20",
    "startTimeGmt": "10:00",
    "venue": "The Rose Bowl, Southampton",
    "day": "One Day Match"
  },
  {
    "matchId": "fe506001-b295-4f2d-95e0-f9084a75100e",
    "competition": "One-Day Cup",
    "homeTeam": "Essex",
    "homeTeamBlueskyHandle": "essexcricket.bsky.social",
    "awayTeam": "Glamorgan",
    "awayTeamBlueskyHandle": "glamcricket.bsky.social",
    "startDate": "2025-08-20",
    "endDate": "2025-08-20",
    "startTimeGmt": "10:00",
    "venue": "County Ground, Chelmsford",
    "day": "One Day Match"
  }
]